README.rst
setup.py
django_metadata.egg-info/PKG-INFO
django_metadata.egg-info/SOURCES.txt
django_metadata.egg-info/dependency_links.txt
django_metadata.egg-info/not-zip-safe
django_metadata.egg-info/pbr.json
django_metadata.egg-info/requires.txt
django_metadata.egg-info/top_level.txt
metadata/__init__.py
metadata/compat.py
metadata/connection.py
metadata/mixins.py
metadata/models.py
metadata/settings.py
metadata/utils.py
metadata/tests/__init__.py
metadata/tests/models.py
metadata/tests/settings.py
metadata/tests/tests.py