Metadata-Version: 1.1
Name: django-metadata
Version: 0.2.0
Summary: Attach metadata to any Django models using redis
Home-page: http://github.com/thoas/django-metadata
Author: Florent Messa
Author-email: florent.messa@gmail.com
License: UNKNOWN
Keywords: django,libraries,settings,redis,metadata
Platform: any
Classifier: Environment :: Web Environment
Classifier: Intended Audience :: Developers
Classifier: License :: OSI Approved :: MIT License
Classifier: Operating System :: OS Independent
Classifier: Programming Language :: Python :: 2.6
Classifier: Programming Language :: Python :: 2.7
Classifier: Programming Language :: Python :: 3.3
Classifier: Topic :: Utilities
